deepseek_claude/__init__.py
deepseek_claude/server.py
iflow_mcp_deepseek_claude-0.1.1.dist-info/licenses/LICENSE
iflow_mcp_deepseek_claude-0.1.1.dist-info/METADATA
iflow_mcp_deepseek_claude-0.1.1.dist-info/WHEEL
iflow_mcp_deepseek_claude-0.1.1.dist-info/entry_points.txt
iflow_mcp_deepseek_claude-0.1.1.dist-info/top_level.txt
iflow_mcp_deepseek_claude-0.1.1.dist-info/RECORD
