Metadata-Version: 2.4
Name: iflow-mcp_deepseek-claude
Version: 0.1.1
Summary: Add your description here
Requires-Python: >=3.11
License-File: LICENSE
Requires-Dist: httpx>=0.28.1
Requires-Dist: mcp[cli]>=1.2.0
Dynamic: license-file
